{
    "item": {
        "id": 133416,
        "origem": 205042,
        "lanceAtual": 22000.0,
        "lanceAtualId": 3185,
        "dataInicio": "2024-01-29T00:00:08",
        "dataFimInicial": "2024-02-28T10:30:00",
        "dataFim": "2024-02-28T10:30:00",
        "cancelado": false,
        "modalidadeId": 1,
        "referencia": "LO1198102024",
        "tipoId": 1,
        "subtipoId": 5,
        "tipologiaId": 1,
        "capa": "files/Verbas_Fotos/verba_104194/17012024171137_800sm.jpg",
        "titulo": "Lote de terreno destinado a constru\u00e7\u00e3o de uma moradia unifamiliar de 2 pisos",
        "valorBase": 26470.0,
        "valorAbertura": 13235.0,
        "valorMinimo": 22499.5,
        "tipo": "Im\u00f3vel",
        "subtipo": "Terreno Constru\u00e7\u00e3o",
        "tipologia": "n\u00e3o aplic\u00e1vel",
        "descricao": "Peda\u00e7o de terreno para constru\u00e7\u00e3o urbana, situado na Herdade do Pomarinho, Lote 25, 7565-119 ERMIDAS-SADO\r\nConfrontando a Norte, lote n\u00ba 24; Sul, terreno camar\u00e1rio; Nascente, Herdade do Pomarinho; Poente, Rua 30.\r\nRegistado na Conservat\u00f3ria do Registo Civil,  Predial, Comercial e Autom\u00f3veis de Santiago do Cac\u00e9m, Freguesia Ermidas-Sado, sob o n\u00ba 658.\r\nInscrito na matriz urbana do Distrito de Set\u00fabal, Concelho de Santiago do Cac\u00e9m, Freguesia de Ermidas-Sado com o artigo matricial 1808",
        "observacoes": "A licita\u00e7\u00e3o tem car\u00e1ter definitivo.\r\nPresume-se que o interessado tenha inspecionado o terreno e conhece as suas caracter\u00edsticas, sendo da sua \u00fanica e exclusiva responsabilidade a verifica\u00e7\u00e3o do estado do bem a adquirir pelo que dever\u00e1, antes de licitar, assegurar-se que o mesmo corresponde \u00e0s suas expectativas e se encontra nas condi\u00e7\u00f5es, f\u00edsicas e legais, pretendidas. \r\nA falta desta verifica\u00e7\u00e3o por parte do proponente n\u00e3o determina, nos termos legais, a anula\u00e7\u00e3o da venda. \r\nEncerrado o Leil\u00e3o, o melhor proponente \u00e9 notificado para depositar, no prazo de 15 dias, o pre\u00e7o oferecido, bem como para proceder ao pagamento dos impostos devidos (artigo 824\u00ba n.\u00ba 2 do C\u00f3digo de Processo Civil). \r\nCaso o n\u00e3o fa\u00e7a incorre nas comina\u00e7\u00f5es previstas no art.\u00ba 825\u00ba do C.P.C. designadamente o arresto de bens pr\u00f3prios do proponente faltoso.\r\nNos termos do disposto no n\u00ba 6 do artigo 833\u00ba do C\u00f3digo de Processo Civil a venda est\u00e1 dispensada da apresenta\u00e7\u00e3o do alvar\u00e1 de loteamento ou outros documentos, sendo da responsabilidade do adquirente eventual legaliza\u00e7\u00e3o.\r\nAconselha-se a leitura atenta das perguntas e respostas em https://www.e-leiloes.pt/faqs.aspx",
        "areaUtilPrivativa": 237.303,
        "areaUtilDependente": 0.0,
        "areaTotal": 237.303,
        "morada": "Ermidas-Sado",
        "moradaNumero": "",
        "moradaAndar": "",
        "moradaDistrito": "Set\u00fabal",
        "moradaConcelho": "Santiago do Cac\u00e9m",
        "moradaFreguesia": "Ermidas-Sado",
        "moradaCP": "7565-119",
        "coordenadasLAT": "38.00020183",
        "coordenadasLON": "-8.38129897",
        "ivaCobrar": false,
        "ivaPercentagem": 23.0,
        "processoId": 70846,
        "processoNumero": "3175/16.3T8STB.",
        "processoComarca": "Comarca de Set\u00fabal",
        "processoComarcaCodigo": "1052",
        "processoTribunal": "Set\u00fabal - Ju\u00edzo Execu\u00e7\u00e3o - Juiz 2",
        "verbaId": 104194,
        "osae360": "",
        "matricula": "",
        "executados": "[{\"nif\":\"103808337\", \"nome\":\"Carlos Albertino Santos Cercas\", \"requerido\":\"False\"}]",
        "cerimoniaId": 897,
        "cerimoniaData": "2024-02-28T14:30:00",
        "cerimoniaLocal": "Lisboa - Pal\u00e1cio da Justi\u00e7a",
        "cerimoniaMorada": "Pal\u00e1cio da Justica, Piso 1 - Rua Marqu\u00eas de Fronteira, 1098-001 Lisboa",
        "gestorId": 423,
        "gestorTipo": "Agente de Execu\u00e7\u00e3o",
        "gestorTipoId": 1,
        "gestorCedula": "5349",
        "gestorNome": "AGOSTINHO CASANOVA",
        "gestorEmail": "5349@solicitador.net",
        "gestorComarca": "",
        "gestorTribunal": "",
        "gestorTelefone": "",
        "gestorFax": "",
        "gestorMorada": "",
        "gestorHorario": "",
        "dataServidor": "2024-02-12T20:10:26",
        "dataAtualizacao": "2024-02-12T20:10:26",
        "iniciado": true,
        "terminado": false,
        "ultimos5m": false,
        "fotos": [
            {
                "legenda": "",
                "image": "files/Verbas_Fotos/verba_104194/17012024171137_800.jpg",
                "thumbnail": "files/Verbas_Fotos/verba_104194/17012024171137_200.jpg"
            },
            {
                "legenda": "",
                "image": "files/Verbas_Fotos/verba_104194/17012024171142_800.jpg",
                "thumbnail": "files/Verbas_Fotos/verba_104194/17012024171142_200.jpg"
            },
            {
                "legenda": "",
                "image": "files/Verbas_Fotos/verba_104194/17012024171146_800.jpg",
                "thumbnail": "files/Verbas_Fotos/verba_104194/17012024171146_200.jpg"
            }
        ],
        "onus": [],
        "descPredial": [
            {
                "id": 32693,
                "numero": "658",
                "fracao": "",
                "distritoDesc": "15 - Set\u00fabal",
                "concelhoDesc": "09 - Santiago do Cac\u00e9m",
                "freguesiaDesc": "04 - Ermidas-sado",
                "artigos": [
                    {
                        "numero": "1808",
                        "tipo": "urbana",
                        "fracao": "",
                        "distritoDesc": "15 - Set\u00fabal",
                        "concelhoDesc": "09 - Santiago do Cac\u00e9m",
                        "freguesiaDesc": "04 - Ermidas-Sado"
                    }
                ]
            }
        ],
        "visitas": [],
        "anexos": [],
        "favorito": false,
        "licitado": false,
        "primeiraProposta": true,
        "informacaoMinima": false
    },
    "messages": false,
    "messagesList": [],
    "errors": false,
    "errorsList": [],
    "exception": false
}